thonnycontrib/error-explainer/__init__.py
thonny_error_explainer-0.9.dist-info/LICENCE.txt
thonny_error_explainer-0.9.dist-info/METADATA
thonny_error_explainer-0.9.dist-info/WHEEL
thonny_error_explainer-0.9.dist-info/top_level.txt
thonny_error_explainer-0.9.dist-info/RECORD
