Metadata-Version: 2.1
Name: thonny-error-explainer
Version: 0.9
Summary: Thonny plugin for error-explainer
Home-page: https://github.com/K44rel/thonny-error-explainer-plugin
Author: Kaarel Loide
Author-email: kaarel.loide@gmail.com
License: UNKNOWN
Platform: UNKNOWN
Classifier: Development Status :: 3 - Alpha
Classifier: Intended Audience :: Developers
Classifier: Topic :: Software Development
Classifier: License :: OSI Approved :: MIT License
Classifier: Programming Language :: Python :: 3.6
Classifier: Programming Language :: Python :: 3.7
Requires-Dist: thonny (>=3.2.1)
Requires-Dist: error-explainer (>=0.14)
